asker/__init__.py
asker/asker.py
asker-0.1.5.dist-info/DESCRIPTION.rst
asker-0.1.5.dist-info/METADATA
asker-0.1.5.dist-info/RECORD
asker-0.1.5.dist-info/WHEEL
asker-0.1.5.dist-info/metadata.json
asker-0.1.5.dist-info/top_level.txt
