Metadata-Version: 2.0
Name: asker
Version: 0.1.5
Summary: Nice cli multiple choice selection and more!
Home-page: https://github.com/kcsaff/asker
Author: K.C.Saff
Author-email: kc@saff.net
License: MIT
Keywords: stdin,command line
Platform: UNKNOWN
Classifier: Development Status :: 5 - Production/Stable
Classifier: Environment :: Console
Classifier: Intended Audience :: Developers
Classifier: License :: OSI Approved :: MIT License
Classifier: Operating System :: OS Independent
Classifier: Programming Language :: Python :: 2.7
Classifier: Programming Language :: Python :: 3.3
Classifier: Programming Language :: Python :: 3.4
Classifier: Programming Language :: Python :: 3.5
Classifier: Topic :: Software Development
Classifier: Topic :: Software Development :: User Interfaces
Requires-Dist: colorama
Requires-Dist: getkey
Requires-Dist: six
